opustag/__init__.py
opustag/cli.py
opustag/main.py
opustag/routers/__init__.py
opustag/routers/library.py
opustag/routers/search.py
opustag/services/__init__.py
opustag/services/itunes.py
opustag/services/tagger.py
opustag/static/index.html
opustag/static/opustag.svg
opustag/static/vite.svg
opustag/static/assets/index-D81CfNOV.css
opustag/static/assets/index-TM8KiNzq.js
opustag-0.2.2.dist-info/licenses/LICENSE
opustag-0.2.2.dist-info/METADATA
opustag-0.2.2.dist-info/WHEEL
opustag-0.2.2.dist-info/entry_points.txt
opustag-0.2.2.dist-info/top_level.txt
opustag-0.2.2.dist-info/RECORD
