Metadata-Version: 2.4
Name: opustag
Version: 0.2.2
Summary: A modern, elegant audio metadata manager designed specifically for classical music collectors.
Author: Xiao Ran
Maintainer-email: Xiao Ran <xiaoran.007@icloud.com>
License-Expression: GPL-3.0-or-later
Project-URL: homepage, https://github.com/xiaoran007/OpusTag
Classifier: Development Status :: 5 - Production/Stable
Classifier: Programming Language :: Python :: 3
Classifier: Operating System :: OS Independent
Requires-Python: >=3.9
License-File: LICENSE
Requires-Dist: fastapi
Requires-Dist: uvicorn[standard]
Requires-Dist: python-multipart
Requires-Dist: requests
Requires-Dist: mutagen
Requires-Dist: pydantic
Dynamic: license-file
